dupecheck/__init__.py
dupecheck/chunks.py
dupecheck/contractions_list.py
dupecheck/preprocess.py
dupecheck/sliding_window.py
dupecheck/sliding_window2.py
dupecheck/utils.py
dupecheck-0.7.1.dist-info/LICENSE.md
dupecheck-0.7.1.dist-info/METADATA
dupecheck-0.7.1.dist-info/WHEEL
dupecheck-0.7.1.dist-info/top_level.txt
dupecheck-0.7.1.dist-info/RECORD
