Metadata-Version: 2.1
Name: dupecheck
Version: 0.7.1
Summary: Check for duplicate word series between generated text and a dataset
Home-page: https://github.com/spacerockzero/dupecheck-py
Author: Jakob Anderson
Author-email: fictionisfiction@gmail.com
License: MIT
Platform: UNKNOWN
Requires-Dist: tqdm
Requires-Dist: nltk
Requires-Dist: autocorrect
